{
    "title": "CROCHET I SKILL LEVEL: EASY",
    "steps": [
        "CROCHET I SKILL LEVEL: EASY\nONE KNIT & ONE CROCHET MOBIUS | CROCHET SHOP KIT\nOne Knit & One Crochet Ch 44.\nRow 1: Sc in 2nd ch from hook, * skip next 2 ch; 5 dc in\nnext ch \u2013 shell made; skip next 2 ch, sc in next ch; repeat\nMobius\nfrom * across; turn \u2013 7 shells.\nRow 2: Ch 3, 2 dc in first sc, * skip next 2 dc, sc in next dc,\nskip next 2 dc **, shell in next sc; repeat from * to last sc,\nend at **; 3 dc in last sc; turn.\nDesigned by Darla Sims Row 3: Ch 1, sc in first dc, * skip next 2 dc, shell in next\nsc, skip next 2 dc, sc in next dc; repeat from * across\nDirections are for size Small; changes for sizes working last sc in top of ch-3; turn.\nMedium, Large and Extra Large, 2X and 3X are in\nparentheses. Repeat Rows 2 and 3 for pattern until 36 (40, 44, 48, 52,\n56)\u201d from beginning, end by working Row 2. Fasten off.\nFInISHInG\nLay crochet strip on a flat surface. Turn beginning ch\nend over to twist strip. Sew edges together while in this\nposition. Weave in ends.\nTO WEAR\nPull over head with twist at front and adjust top to cover\nshoulders as desired OR, pull down to waist with seam at\ncenter back, then pull the front of circle up over your head.\nAdjust piece to fit and fold back collar.\nCROCHET SHELLS MOBIUS\nTo Fit Bust: 32 (36, 30, 44, 48, 52)\u201d.\nFinished Measurements: 16\u201d x 36 (40, 44, 48, 52, 56)\u201d.\nRED HEART\u00ae \u201cHoliday\u201d: 2 Balls 9040 Red/Silver.\nCrochet Hook: 6.5mm [US K-10.5].\nYarn needle.\nGAUGE: 2 Shells = 41/ \u201d. CHECK YOUR GAUGE. Use\n2 KnIT MOBIUS WRAP\nany size hook to obtain the gauge.\nFinished Chest: 36 (40, 44, 48, 52, 56)\u201d\nFinished Length: 16\u201d\nFor more ideas & inspiration \u2014\n\u00a92010 Coats & Clark\nP.O. Box 12229 www.redheart.com www.coatsandclark.com\nGreenville, SC 29612-0229\nwww.crochettoday.com\nRHC0107-023500M | LAST UPDATED: AUGUST 2019 ONE KNIT & ONE CROCHET MOBIUS | CROCHET 1 of 2\nCROCHET I SKILL LEVEL: EASY\nONE KNIT & ONE CROCHET MOBIUS | CROCHET\nRED HEART\u00ae \u201cHoliday\u201d: 2 (2, 2, 3, 3, 3) skeins 1360\nAran/Gold\nKnitting needles: 6.5mm [US 10\u00bd].\nYarn needle.\nGAUGE: 14 sts = 4\u201d; 26 rows = 4\u201d in Garter stitch. CHECK\nYOUR GAUGE. Use any size needles to obtain the\nspecified gauge.\nCast on 56 stitches.\nKnit every row until piece measures 36 (40, 44, 48, 52,\n56)\u201d from beginning.\nBind off.\nFInISHInG\nSew cast-on row to bind-off row, turning one end over to\nsew wrong side of one end to right side of opposite end to\nput a twist in length.\nWeave in ends.\nRED HEART\u00ae \u201cHoliday\u201d, Art. E759\navailable in 3.5 oz (100 g), 251 yd (230 m)\nballs.\nABBREVIATIOnS: ch = chain; dc = double crochet;\nmm = millimeters; sc = single crochet; * or ** = repeat\nwhatever follows the * or ** as indicated.\nFor more ideas & inspiration \u2014\n\u00a92010 Coats & Clark\nRHC0107-023500M | PLA.OS.T B UoPxD 1A2T2E2D9: AUGUST 2019 www.redheart.com ONE KNIwT &w OwN.Ec CoRaOtCsHaEnTd McOlaBIrUkS. c| CoRmOCHET 2 of 2\nGreenville, SC 29612-0229\nwww.crochettoday.com"
    ],
    "entities": [
        {
            "text": "CROCHET",
            "label": "ORG"
        },
        {
            "text": "ONE",
            "label": "CARDINAL"
        },
        {
            "text": "ONE",
            "label": "CARDINAL"
        },
        {
            "text": "CROCHET",
            "label": "ORG"
        },
        {
            "text": "KIT",
            "label": "ORG"
        },
        {
            "text": "One",
            "label": "CARDINAL"
        },
        {
            "text": "One",
            "label": "CARDINAL"
        },
        {
            "text": "44",
            "label": "DATE"
        },
        {
            "text": "1",
            "label": "CARDINAL"
        },
        {
            "text": "2nd",
            "label": "ORDINAL"
        },
        {
            "text": "next 2",
            "label": "DATE"
        },
        {
            "text": "5",
            "label": "CARDINAL"
        },
        {
            "text": "next 2",
            "label": "DATE"
        },
        {
            "text": "Mobius",
            "label": "PERSON"
        },
        {
            "text": "7",
            "label": "CARDINAL"
        },
        {
            "text": "2",
            "label": "CARDINAL"
        },
        {
            "text": "first",
            "label": "ORDINAL"
        },
        {
            "text": "next 2",
            "label": "DATE"
        },
        {
            "text": "next 2",
            "label": "DATE"
        },
        {
            "text": "3",
            "label": "CARDINAL"
        },
        {
            "text": "Darla Sims Row",
            "label": "PERSON"
        },
        {
            "text": "3",
            "label": "CARDINAL"
        },
        {
            "text": "first",
            "label": "ORDINAL"
        },
        {
            "text": "next 2",
            "label": "DATE"
        },
        {
            "text": "next 2",
            "label": "DATE"
        },
        {
            "text": "Extra Large",
            "label": "ORG"
        },
        {
            "text": "2X",
            "label": "CARDINAL"
        },
        {
            "text": "3X",
            "label": "CARDINAL"
        },
        {
            "text": "2",
            "label": "CARDINAL"
        },
        {
            "text": "3",
            "label": "CARDINAL"
        },
        {
            "text": "36",
            "label": "CARDINAL"
        },
        {
            "text": "40,",
            "label": "DATE"
        },
        {
            "text": "44",
            "label": "DATE"
        },
        {
            "text": "48",
            "label": "DATE"
        },
        {
            "text": "52",
            "label": "DATE"
        },
        {
            "text": "56",
            "label": "CARDINAL"
        },
        {
            "text": "2",
            "label": "CARDINAL"
        },
        {
            "text": "32",
            "label": "CARDINAL"
        },
        {
            "text": "36",
            "label": "DATE"
        },
        {
            "text": "30",
            "label": "DATE"
        },
        {
            "text": "44",
            "label": "DATE"
        },
        {
            "text": "48",
            "label": "DATE"
        },
        {
            "text": "52",
            "label": "DATE"
        },
        {
            "text": "16",
            "label": "CARDINAL"
        },
        {
            "text": "36",
            "label": "DATE"
        },
        {
            "text": "40, 44",
            "label": "DATE"
        },
        {
            "text": "48",
            "label": "DATE"
        },
        {
            "text": "52",
            "label": "DATE"
        },
        {
            "text": "56",
            "label": "DATE"
        },
        {
            "text": "2",
            "label": "CARDINAL"
        },
        {
            "text": "6.5",
            "label": "CARDINAL"
        },
        {
            "text": "US",
            "label": "GPE"
        },
        {
            "text": "Yarn",
            "label": "PERSON"
        },
        {
            "text": "GAUGE",
            "label": "ORG"
        },
        {
            "text": "2",
            "label": "CARDINAL"
        },
        {
            "text": "41/",
            "label": "DATE"
        },
        {
            "text": "2",
            "label": "CARDINAL"
        },
        {
            "text": "KnIT MOBIUS WRAP",
            "label": "ORG"
        },
        {
            "text": "36",
            "label": "CARDINAL"
        },
        {
            "text": "40,",
            "label": "DATE"
        },
        {
            "text": "44",
            "label": "DATE"
        },
        {
            "text": "48",
            "label": "DATE"
        },
        {
            "text": "52",
            "label": "DATE"
        },
        {
            "text": "56",
            "label": "DATE"
        },
        {
            "text": "Finished Length",
            "label": "PERSON"
        },
        {
            "text": "16",
            "label": "CARDINAL"
        },
        {
            "text": "2010",
            "label": "DATE"
        },
        {
            "text": "Coats & Clark\nP.O. Box",
            "label": "ORG"
        },
        {
            "text": "12229",
            "label": "DATE"
        },
        {
            "text": "Greenville",
            "label": "GPE"
        },
        {
            "text": "SC",
            "label": "ORG"
        },
        {
            "text": "29612-0229",
            "label": "DATE"
        },
        {
            "text": "AUGUST 2019",
            "label": "DATE"
        },
        {
            "text": "ONE",
            "label": "CARDINAL"
        },
        {
            "text": "KNIT & ONE",
            "label": "ORG"
        },
        {
            "text": "1",
            "label": "CARDINAL"
        },
        {
            "text": "2",
            "label": "CARDINAL"
        },
        {
            "text": "ONE",
            "label": "CARDINAL"
        },
        {
            "text": "ONE",
            "label": "CARDINAL"
        },
        {
            "text": "CROCHET\nRED HEART\u00ae",
            "label": "ORG"
        },
        {
            "text": "2",
            "label": "CARDINAL"
        },
        {
            "text": "2",
            "label": "CARDINAL"
        },
        {
            "text": "2",
            "label": "DATE"
        },
        {
            "text": "3",
            "label": "DATE"
        },
        {
            "text": "3",
            "label": "DATE"
        },
        {
            "text": "3",
            "label": "CARDINAL"
        },
        {
            "text": "1360",
            "label": "DATE"
        },
        {
            "text": "Aran/Gold\nKnitting",
            "label": "WORK_OF_ART"
        },
        {
            "text": "6.5mm",
            "label": "QUANTITY"
        },
        {
            "text": "US",
            "label": "GPE"
        },
        {
            "text": "Yarn",
            "label": "PERSON"
        },
        {
            "text": "GAUGE",
            "label": "ORG"
        },
        {
            "text": "14",
            "label": "CARDINAL"
        },
        {
            "text": "4",
            "label": "CARDINAL"
        },
        {
            "text": "26",
            "label": "CARDINAL"
        },
        {
            "text": "4",
            "label": "CARDINAL"
        },
        {
            "text": "Garter",
            "label": "GPE"
        },
        {
            "text": "GAUGE",
            "label": "ORG"
        },
        {
            "text": "Cast",
            "label": "PERSON"
        },
        {
            "text": "56",
            "label": "CARDINAL"
        },
        {
            "text": "Knit",
            "label": "PERSON"
        },
        {
            "text": "36",
            "label": "DATE"
        },
        {
            "text": "40, 44",
            "label": "DATE"
        },
        {
            "text": "48",
            "label": "DATE"
        },
        {
            "text": "52",
            "label": "DATE"
        },
        {
            "text": "56",
            "label": "CARDINAL"
        },
        {
            "text": "Bind",
            "label": "ORG"
        },
        {
            "text": "one",
            "label": "CARDINAL"
        },
        {
            "text": "Art",
            "label": "PERSON"
        },
        {
            "text": "3.5",
            "label": "CARDINAL"
        },
        {
            "text": "100",
            "label": "CARDINAL"
        },
        {
            "text": "251 yd",
            "label": "QUANTITY"
        },
        {
            "text": "230",
            "label": "CARDINAL"
        },
        {
            "text": "2010",
            "label": "DATE"
        },
        {
            "text": "Coats & Clark\nRHC0107-023500M",
            "label": "ORG"
        },
        {
            "text": "1A2T2E2D9",
            "label": "CARDINAL"
        },
        {
            "text": "AUGUST 2019",
            "label": "DATE"
        },
        {
            "text": "ONE",
            "label": "CARDINAL"
        },
        {
            "text": "McOlaBIrUkS. c| CoRmOCHET 2",
            "label": "ORG"
        },
        {
            "text": "2",
            "label": "CARDINAL"
        },
        {
            "text": "Greenville",
            "label": "GPE"
        },
        {
            "text": "SC",
            "label": "ORG"
        },
        {
            "text": "29612-0229",
            "label": "DATE"
        }
    ]
}